jisho_api/__init__.py
jisho_api/cli.py
jisho_api/kanji/__init__.py
jisho_api/kanji/cfg.py
jisho_api/kanji/request.py
jisho_api/sentence/__init__.py
jisho_api/sentence/cfg.py
jisho_api/sentence/request.py
jisho_api/tokenize/__init__.py
jisho_api/tokenize/cfg.py
jisho_api/tokenize/request.py
jisho_api/util.py
jisho_api/word/__init__.py
jisho_api/word/cfg.py
jisho_api/word/request.py
jisho_api-0.1.6.dist-info/entry_points.txt
jisho_api-0.1.6.dist-info/LICENSE.txt
jisho_api-0.1.6.dist-info/WHEEL
jisho_api-0.1.6.dist-info/METADATA
jisho_api-0.1.6.dist-info/RECORD
