Metadata-Version: 2.1
Name: jisho-api
Version: 0.1.6
Summary: A jisho.org API and scraper in Python.
Home-page: https://github.com/pedroallenrevez/jisho-api
License: Apache-2.0
Keywords: jisho,japanese,api,scraper,kanji,python
Author: pedro
Author-email: pedroallenrevez@gmail.com
Requires-Python: >=3.7.1,<4.0.0
Classifier: License :: OSI Approved :: Apache Software License
Classifier: Programming Language :: Python :: 3
Classifier: Programming Language :: Python :: 3.10
Classifier: Programming Language :: Python :: 3.8
Classifier: Programming Language :: Python :: 3.9
Requires-Dist: bs4 (>=0.0.1,<0.0.2)
Requires-Dist: click (>=8.0.1,<9.0.0)
Requires-Dist: pydantic (>=1.8.2,<2.0.0)
Requires-Dist: requests (>=2.26.0,<3.0.0)
Requires-Dist: rich (>=10.11.0,<11.0.0)
Project-URL: Repository, https://github.com/pedroallenrevez/jisho-api
